lydite/__init__.py
lydite/data/__init__.py
lydite-0.0.2.dist-info/METADATA
lydite-0.0.2.dist-info/WHEEL
lydite-0.0.2.dist-info/top_level.txt
lydite-0.0.2.dist-info/RECORD
